multiagent_debugger/__init__.py
multiagent_debugger/__main__.py
multiagent_debugger/cli.py
multiagent_debugger/config.py
multiagent_debugger/crew.py
multiagent_debugger/agents/__init__.py
multiagent_debugger/agents/code_agent.py
multiagent_debugger/agents/code_path_analyzer_agent.py
multiagent_debugger/agents/log_agent.py
multiagent_debugger/agents/question_analyzer_agent.py
multiagent_debugger/agents/root_cause_agent.py
multiagent_debugger/tools/__init__.py
multiagent_debugger/tools/code_tools.py
multiagent_debugger/tools/flowchart_tool.py
multiagent_debugger/tools/log_tools.py
multiagent_debugger/utils/__init__.py
multiagent_debugger/utils/constants.py
multiagent_debugger/utils/llm_config.py
multiagent_debugger/utils/phoenix_monitor.py
multiagent_debugger-1.0.24.dist-info/licenses/LICENSE
multiagent_debugger-1.0.24.dist-info/METADATA
multiagent_debugger-1.0.24.dist-info/WHEEL
multiagent_debugger-1.0.24.dist-info/entry_points.txt
multiagent_debugger-1.0.24.dist-info/top_level.txt
multiagent_debugger-1.0.24.dist-info/RECORD
