Metadata-Version: 2.4
Name: multiagent-debugger
Version: 1.0.24
Summary: A multi-agent system for debugging API failures
Home-page: https://github.com/VishApp/multiagent-debugger
Author: Vishnu Prasad
Author-email: vishnuprasadapp@gmail.com
Project-URL: Bug Tracker, https://github.com/VishApp/multiagent-debugger/issues
Project-URL: Documentation, https://github.com/VishApp/multiagent-debugger#readme
Project-URL: Source Code, https://github.com/VishApp/multiagent-debugger
Keywords: debugger,api,multi-agent,crewai,llm,openai,anthropic,debugging
Classifier: Development Status :: 4 - Beta
Classifier: Intended Audience :: Developers
Classifier: Topic :: Software Development :: Debuggers
Classifier: Topic :: Software Development :: Libraries :: Application Frameworks
Classifier: Programming Language :: Python :: 3
Classifier: Programming Language :: Python :: 3.8
Classifier: Programming Language :: Python :: 3.9
Classifier: Programming Language :: Python :: 3.10
Classifier: License :: OSI Approved :: MIT License
Classifier: Operating System :: OS Independent
Requires-Python: >=3.8
License-File: LICENSE
Requires-Dist: crewai>=0.28.0
Requires-Dist: pydantic>=2.0.0
Requires-Dist: python-dotenv>=1.0.0
Requires-Dist: typer[all]>=0.9.0
Requires-Dist: openai>=1.0.0
Requires-Dist: anthropic>=0.8.0
Requires-Dist: colorlog>=6.7.0
Requires-Dist: tree-sitter>=0.20.1
Requires-Dist: gitpython>=3.1.31
Requires-Dist: pyyaml>=6.0
Requires-Dist: rich>=13.4.2
Requires-Dist: requests>=2.25.0
Requires-Dist: arize-phoenix
Requires-Dist: arize-phoenix-otel
Requires-Dist: opentelemetry-api
Requires-Dist: opentelemetry-sdk
Requires-Dist: opentelemetry-instrumentation
Requires-Dist: opentelemetry-instrumentation-openai
Requires-Dist: opentelemetry-instrumentation-requests
Requires-Dist: openinference-instrumentation-openai
Requires-Dist: opentelemetry-instrumentation
Requires-Dist: openinference-instrumentation-anthropic
Requires-Dist: openinference-instrumentation-google-genai
Requires-Dist: openinference-instrumentation-groq
Requires-Dist: openinference-instrumentation-mistralai
Requires-Dist: psutil>=5.8.0
Dynamic: author
Dynamic: author-email
Dynamic: classifier
Dynamic: description
Dynamic: description-content-type
Dynamic: home-page
Dynamic: keywords
Dynamic: license-file
Dynamic: project-url
Dynamic: requires-dist
Dynamic: requires-python
Dynamic: summary
